minchin/pelican/plugins/post_stats/__init__.py
minchin/pelican/plugins/post_stats/post_stats.py
minchin/pelican/plugins/post_stats/readability.py
minchin_pelican_plugins_post_stats-1.3.1.dist-info/licenses/LICENSE.txt
minchin_pelican_plugins_post_stats-1.3.1.dist-info/METADATA
minchin_pelican_plugins_post_stats-1.3.1.dist-info/WHEEL
minchin_pelican_plugins_post_stats-1.3.1.dist-info/top_level.txt
minchin_pelican_plugins_post_stats-1.3.1.dist-info/RECORD
